grappy/__init__.py
grappy/main.py
GrapPY_lfjv-0.0.3.dist-info/LICENSE
GrapPY_lfjv-0.0.3.dist-info/METADATA
GrapPY_lfjv-0.0.3.dist-info/WHEEL
GrapPY_lfjv-0.0.3.dist-info/top_level.txt
GrapPY_lfjv-0.0.3.dist-info/RECORD
