Metadata-Version: 2.1
Name: GrapPY-lfjv
Version: 0.0.3
Summary: Simplification de la création de graphiques avec matplotlib
Home-page: https://github.com/pypa/sampleproject
Author: Benjamin Trévian
Author-email: benjamin.trevian@hotmail.com
Project-URL: Bug Tracker, https://github.com/pypa/sampleproject/issues
Classifier: Programming Language :: Python :: 3
Classifier: License :: OSI Approved :: MIT License
Classifier: Operating System :: OS Independent
Requires-Python: >=3.6
License-File: LICENSE
Requires-Dist: matplotlib
